{
  "paper_id": "2023214397_李锦浩",
  "student_number": "2023214397",
  "student_name": "李锦浩",
  "source_image": "D:\\grade code\\homework-grader\\software-project-practicum\\workspace\\practicum-batch\\raw\\软件需求答题卡扫描件\\A13251A2130620002\\2023214397_李锦浩.jpg",
  "total_score": 58.0,
  "section_scores": {
    "single_choice": 10.0,
    "true_false": 6.0,
    "fill_blank": 4.0,
    "short_answer": 11.0,
    "comprehensive": 25.0
  },
  "question_scores": {
    "26": 0.0,
    "27": 5.0,
    "28": 1.0,
    "29": 5.0,
    "30": 5.0,
    "31": 7.0,
    "32": 8.0,
    "33": 5.0
  },
  "checks": {
    "total_score_present": true,
    "single_choice_score_present": true,
    "true_false_score_present": true,
    "fill_blank_score_present": true,
    "q26_score_present": true,
    "q27_score_present": true,
    "q28_score_present": true,
    "q29_score_present": true,
    "q30_score_present": true,
    "q31_score_present": true,
    "q32_score_present": true,
    "q33_score_present": true,
    "computed_short_answer_sum": 11.0,
    "computed_comprehensive_sum": 25.0,
    "computed_total": 56.0,
    "missing_score_fields": [],
    "sum_matches_total": false,
    "issues": [
      "section_sum_not_match_total"
    ]
  },
  "notes": [
    "总分在顶部汇总表中为58。",
    "客观题分数分别标注为：单选10、判断6、填空4。",
    "第26题右上角得分看起来为0（满分5）。",
    "第30题得分为5，第31题得分为7。",
    "根据每题右上方红字“得分”提取最终分数。",
    "已忽略红色对勾、叉号以及题内局部“+2”批注，它们不是题目最终得分。",
    "section_sum_not_match_total"
  ],
  "needs_review": true,
  "confidence": {
    "overall": 0.72,
    "total_score": 0.98,
    "question_scores": 0.9
  },
  "normalization": {
    "source_size": [
      2199,
      3110
    ],
    "normalized_size": [
      2199,
      3110
    ],
    "crop_bbox": [
      28,
      56,
      2174,
      3062
    ],
    "corners_found": true,
    "corners": {
      "top_left": [
        47.0,
        74.0
      ],
      "top_right": [
        2156.5,
        74.0
      ],
      "bottom_right": [
        2156.5,
        3044.0
      ],
      "bottom_left": [
        46.5,
        3044.5
      ]
    }
  }
}